LICENSE
MANIFEST.in
README.md
lodgeitlib.py
setup.py
pastelib.egg-info/PKG-INFO
pastelib.egg-info/SOURCES.txt
pastelib.egg-info/dependency_links.txt
pastelib.egg-info/top_level.txt