Metadata-Version: 1.1
Name: pastelib
Version: 0.6.1
Summary: Python module to interact with lodgeit/spacepaste pastebins
Home-page: https://github.com/TC01/pastelib
Author: Ben Rosser
Author-email: rosser.bjr@gmail.com
License: MIT
Keywords: pastebin lodgeit lodgeitlib spacepaste bpaste
Platform: UNKNOWN
Classifier: Development Status :: 5 - Production/Stable
Classifier: Intended Audience :: Developers
Classifier: Topic :: Software Development :: Libraries
Classifier: Topic :: Software Development :: Libraries :: Python Modules
Classifier: Topic :: Internet :: WWW/HTTP
Classifier: Topic :: Internet :: WWW/HTTP :: Dynamic Content
Classifier: License :: OSI Approved :: MIT License
Classifier: Programming Language :: Python :: 2
Classifier: Programming Language :: Python :: 2.7
